artanis/__init__.py
artanis/_version.py
artanis/application.py
artanis/asgi.py
artanis/events.py
artanis/exceptions.py
artanis/handlers.py
artanis/logging.py
artanis/py.typed
artanis/request.py
artanis/routing.py
artanis/cli/__init__.py
artanis/cli/main.py
artanis/cli/commands/__init__.py
artanis/cli/commands/new.py
artanis/cli/templates/basic/README.md
artanis/cli/templates/basic/app.py
artanis/cli/templates/basic/requirements.txt
artanis/middleware/__init__.py
artanis/middleware/chain.py
artanis/middleware/core.py
artanis/middleware/exception.py
artanis/middleware/response.py
artanis/middleware/security.py
artanis/openapi/__init__.py
artanis/openapi/decorators.py
artanis/openapi/docs.py
artanis/openapi/schema.py
artanis/openapi/spec.py
artanis/openapi/validation.py
artanis-0.1.4.dist-info/licenses/LICENSE
artanis-0.1.4.dist-info/METADATA
artanis-0.1.4.dist-info/WHEEL
artanis-0.1.4.dist-info/entry_points.txt
artanis-0.1.4.dist-info/top_level.txt
artanis-0.1.4.dist-info/RECORD
