Metadata-Version: 2.4
Name: artanis
Version: 0.1.4
Summary: A simple, yet fast, Python framework with named routes
Author-email: Asep Norzai <nordxai@gmail.com>
Maintainer-email: Asep Norzai <nordxai@gmail.com>
License: MIT
Project-URL: Homepage, https://github.com/nordxai/Artanis
Project-URL: Repository, https://github.com/nordxai/Artanis
Project-URL: Bug Reports, https://github.com/nordxai/Artanis/issues
Project-URL: Source Code, https://github.com/nordxai/Artanis
Project-URL: Issues, https://github.com/nordxai/Artanis/issues
Project-URL: Changelog, https://github.com/nordxai/Artanis/releases
Project-URL: Discussions, https://github.com/nordxai/Artanis/discussions
Keywords: asgi,web,framework,async,routes,middleware,logging,express,python,http,api,rest,enterprise,professional
Classifier: Development Status :: 4 - Beta
Classifier: Environment :: Web Environment
Classifier: Framework :: AsyncIO
Classifier: Intended Audience :: Developers
Classifier: Intended Audience :: Information Technology
Classifier: Intended Audience :: System Administrators
Classifier: License :: OSI Approved :: MIT License
Classifier: Natural Language :: English
Classifier: Operating System :: OS Independent
Classifier: Programming Language :: Python
Classifier: Programming Language :: Python :: 3
Classifier: Programming Language :: Python :: 3.8
Classifier: Programming Language :: Python :: 3.9
Classifier: Programming Language :: Python :: 3.10
Classifier: Programming Language :: Python :: 3.11
Classifier: Programming Language :: Python :: 3.12
Classifier: Programming Language :: Python :: 3.13
Classifier: Programming Language :: Python :: 3 :: Only
Classifier: Topic :: Internet
Classifier: Topic :: Internet :: WWW/HTTP
Classifier: Topic :: Internet :: WWW/HTTP :: HTTP Servers
Classifier: Topic :: Internet :: WWW/HTTP :: WSGI
Classifier: Topic :: Internet :: WWW/HTTP :: WSGI :: Application
Classifier: Topic :: Internet :: WWW/HTTP :: WSGI :: Middleware
Classifier: Topic :: Software Development
Classifier: Topic :: Software Development :: Libraries
Classifier: Topic :: Software Development :: Libraries :: Application Frameworks
Classifier: Topic :: Software Development :: Libraries :: Python Modules
Classifier: Topic :: System :: Logging
Classifier: Topic :: System :: Monitoring
Classifier: Typing :: Typed
Requires-Python: >=3.8
License-File: LICENSE
Provides-Extra: dev
Requires-Dist: pytest>=7.0.0; extra == "dev"
Requires-Dist: pytest-asyncio>=0.21.0; extra == "dev"
Requires-Dist: ruff>=0.4.0; extra == "dev"
Requires-Dist: mypy>=1.0.0; extra == "dev"
Requires-Dist: pre-commit>=2.20.0; extra == "dev"
Provides-Extra: test
Requires-Dist: pytest>=7.0.0; extra == "test"
Requires-Dist: pytest-asyncio>=0.21.0; extra == "test"
Requires-Dist: pytest-cov>=3.0.0; extra == "test"
Requires-Dist: coverage>=6.0.0; extra == "test"
Provides-Extra: openapi
Provides-Extra: all
Requires-Dist: artanis[dev,openapi,test]; extra == "all"
Dynamic: license-file
